dropletevapmodel/__init__.py
dropletevapmodel/_utils.py
dropletevapmodel/_version.py
dropletevapmodel/model.py
dropletevapmodel/phy_utils.py
dropletevapmodel/post_process.py
dropletevapmodel/models/phy_model.py
dropletevapmodel-0.2.1.dist-info/LICENSE
dropletevapmodel-0.2.1.dist-info/METADATA
dropletevapmodel-0.2.1.dist-info/WHEEL
dropletevapmodel-0.2.1.dist-info/top_level.txt
dropletevapmodel-0.2.1.dist-info/zip-safe
dropletevapmodel-0.2.1.dist-info/RECORD
