Metadata-Version: 2.1
Name: dropletevapmodel
Version: 0.2.1
Summary: Droplet 0D evaporation model
Author-email: Tommaso Gallingani <t.gallingani@gmail.com>
License-File: LICENSE
Requires-Dist: pandas
Requires-Dist: numpy
Requires-Dist: matplotlib
Requires-Dist: seaborn
Requires-Dist: Pyyaml
Requires-Dist: tqdm
Requires-Dist: pydantic
